strideformer/__init__.py
strideformer/collator.py
strideformer/config.py
strideformer/model.py
strideformer/pipeline.py
strideformer/tokenizer.py
strideformer-0.1.3.dist-info/LICENSE
strideformer-0.1.3.dist-info/METADATA
strideformer-0.1.3.dist-info/WHEEL
strideformer-0.1.3.dist-info/top_level.txt
strideformer-0.1.3.dist-info/RECORD
